{"_type":"export","__export_format":4,"__export_date":"2022-07-25T02:59:45.785Z","__export_source":"insomnia.desktop.app:v2022.4.2","resources":[{"_id":"req_03ca326ba5904aa8b02cbd622cbdc6d9","parentId":"fld_42ab484ef7c64392a28b54207cdaec65","modified":1658672120893,"created":1658447537916,"url":"{{ _.baseUrl }}/coin","name":"List Coins","description":"","method":"GET","body":{},"parameters":[],"headers":[],"authentication":{},"metaSortKey":-1658447510585,"isPrivate":false,"settingStoreCookies":true,"settingSendCookies":true,"settingDisableRenderRequestBody":false,"settingEncodeUrl":true,"settingRebuildPath":true,"settingFollowRedirects":"global","_type":"request"},{"_id":"fld_42ab484ef7c64392a28b54207cdaec65","parentId":"wrk_8ea58a038c744f579cfef9ffbb7f3665","modified":1658447249593,"created":1658447249593,"name":"Coins","description":"","environment":{},"environmentPropertyOrder":null,"metaSortKey":-1658447249593,"_type":"request_group"},{"_id":"wrk_8ea58a038c744f579cfef9ffbb7f3665","parentId":null,"modified":1658672386790,"created":1658242406224,"name":"Dacxi Test Backend","description":"","scope":"collection","_type":"workspace"},{"_id":"req_2e206fecd391412281524e2d922a07c0","parentId":"fld_42ab484ef7c64392a28b54207cdaec65","modified":1658672125094,"created":1658447531522,"url":"{{ _.baseUrl }}/coin/bitcoin","name":"Get Coin","description":"","method":"GET","body":{},"parameters":[],"headers":[],"authentication":{},"metaSortKey":-1658447510560,"isPrivate":false,"settingStoreCookies":true,"settingSendCookies":true,"settingDisableRenderRequestBody":false,"settingEncodeUrl":true,"settingRebuildPath":true,"settingFollowRedirects":"global","_type":"request"},{"_id":"req_c74543b03d7645f094789b2423f6879f","parentId":"fld_42ab484ef7c64392a28b54207cdaec65","modified":1658716813568,"created":1658447510535,"url":"{{ _.baseUrl }}/coin/bitcoin","name":"Create Coin","description":"","method":"POST","body":{"mimeType":"application/json","text":"{\n\t\"id\": \"bitcoin\",\n\t\"coin_id\": \"bitcoin\",\n\t\"name\": \"Bitcoin\",\n\t\"symbol\": \"btc\"\n}"},"parameters":[],"headers":[{"name":"Content-Type","value":"application/json","id":"pair_f81f15bbc6a54e4fac9e5c103517c7ae"},{"id":"pair_466656f856204de28cffd279f2a1a002","name":"Accept","value":"application/json","description":""},{"id":"pair_64d2e502f842470589192a0323bd7bdc","name":"","value":"","description":""}],"authentication":{},"metaSortKey":-1658447510535,"isPrivate":false,"settingStoreCookies":true,"settingSendCookies":true,"settingDisableRenderRequestBody":false,"settingEncodeUrl":true,"settingRebuildPath":true,"settingFollowRedirects":"global","_type":"request"},{"_id":"req_ef433110ea88461f924c219f88e02086","parentId":"fld_42ab484ef7c64392a28b54207cdaec65","modified":1658716380890,"created":1658447521721,"url":"{{ _.baseUrl }}/coin/bitcoin","name":"Update Coin","description":"","method":"PUT","body":{"mimeType":"application/json","text":"{\n\t\"coin_id\": \"bitcoin\",\n\t\"name\": \"Bitcoin\",\n\t\"symbol\": \"btc\"\n}"},"parameters":[],"headers":[{"name":"Content-Type","value":"application/json","id":"pair_fd3ff54423f14de897fafefeab3fb069"},{"id":"pair_7b7c7c33990c44d2b755ba6e4ad2b107","name":"Accept","value":"application/json","description":""}],"authentication":{},"metaSortKey":-1658347220790.25,"isPrivate":false,"settingStoreCookies":true,"settingSendCookies":true,"settingDisableRenderRequestBody":false,"settingEncodeUrl":true,"settingRebuildPath":true,"settingFollowRedirects":"global","_type":"request"},{"_id":"req_0e86d85e33544c9292aa2d47096c8755","parentId":"fld_42ab484ef7c64392a28b54207cdaec65","modified":1658711992291,"created":1658447547478,"url":"{{ _.baseUrl }}/coin/bitcoin","name":"Delete Coin","description":"","method":"DELETE","body":{},"parameters":[],"headers":[],"authentication":{},"metaSortKey":-1658259467263.5938,"isPrivate":false,"settingStoreCookies":true,"settingSendCookies":true,"settingDisableRenderRequestBody":false,"settingEncodeUrl":true,"settingRebuildPath":true,"settingFollowRedirects":"global","_type":"request"},{"_id":"req_7ce9d2e60da14ab281f4452d59aebd1b","parentId":"fld_bc3419d3b65a4e01ac3c3dd072140635","modified":1658672009490,"created":1658253686146,"url":"{{ _.baseUrl }}/crypto/last-price-bitcoin","name":"Last Price Bitcoin","description":"","method":"GET","body":{},"parameters":[],"headers":[],"authentication":{},"metaSortKey":-1658246931045.5,"isPrivate":false,"settingStoreCookies":true,"settingSendCookies":true,"settingDisableRenderRequestBody":false,"settingEncodeUrl":true,"settingRebuildPath":true,"settingFollowRedirects":"global","_type":"request"},{"_id":"fld_bc3419d3b65a4e01ac3c3dd072140635","parentId":"wrk_8ea58a038c744f579cfef9ffbb7f3665","modified":1658447245245,"created":1658447245245,"name":"Historic Price","description":"","environment":{},"environmentPropertyOrder":null,"metaSortKey":-1658447245245,"_type":"request_group"},{"_id":"req_892525b24acc459799c046a4a287c528","parentId":"fld_bc3419d3b65a4e01ac3c3dd072140635","modified":1658713569495,"created":1658254246889,"url":"{{ _.baseUrl }}/crypto/price-datetime-bitcoin?date=2022-07-25&time=01:30:09","name":"Price Datetime Bitcoin","description":"","method":"GET","body":{},"parameters":[],"headers":[],"authentication":{},"metaSortKey":-1658246931033,"isPrivate":false,"settingStoreCookies":true,"settingSendCookies":true,"settingDisableRenderRequestBody":false,"settingEncodeUrl":true,"settingRebuildPath":true,"settingFollowRedirects":"global","_type":"request"},{"_id":"req_4e92834c72474db297885462c7fc1edc","parentId":"fld_bc3419d3b65a4e01ac3c3dd072140635","modified":1658712150485,"created":1658447368051,"url":"{{ _.baseUrl }}/crypto/last-price-coin?coin_id=terra-luna","name":"Last Price Coin","description":"","method":"GET","body":{},"parameters":[],"headers":[],"authentication":{},"metaSortKey":-1658246931020.5,"isPrivate":false,"settingStoreCookies":true,"settingSendCookies":true,"settingDisableRenderRequestBody":false,"settingEncodeUrl":true,"settingRebuildPath":true,"settingFollowRedirects":"global","_type":"request"},{"_id":"req_7d01f87fd6164303aec15e6a38b7f516","parentId":"fld_bc3419d3b65a4e01ac3c3dd072140635","modified":1658717932610,"created":1658447398361,"url":"{{ _.baseUrl }}/crypto/price-datetime-coin?coin_id=dacxi&date=2022-07-25&time=01:30:09","name":"Price Datetime Coin","description":"","method":"GET","body":{},"parameters":[],"headers":[],"authentication":{},"metaSortKey":-1658246930970.5,"isPrivate":false,"settingStoreCookies":true,"settingSendCookies":true,"settingDisableRenderRequestBody":false,"settingEncodeUrl":true,"settingRebuildPath":true,"settingFollowRedirects":"global","_type":"request"},{"_id":"req_10876ea219e040de8b4dd127892fdced","parentId":"fld_bc3419d3b65a4e01ac3c3dd072140635","modified":1658717870652,"created":1658431635556,"url":"{{ _.baseUrl }}/crypto/historic?coin_id=dacxi","name":"Historic Coin","description":"","method":"GET","body":{},"parameters":[],"headers":[],"authentication":{},"metaSortKey":-1658246930958,"isPrivate":false,"settingStoreCookies":true,"settingSendCookies":true,"settingDisableRenderRequestBody":false,"settingEncodeUrl":true,"settingRebuildPath":true,"settingFollowRedirects":"global","_type":"request"},{"_id":"req_b5d8569989314b7d8754a2e66d1533b9","parentId":"fld_bc3419d3b65a4e01ac3c3dd072140635","modified":1658710391413,"created":1658709959168,"url":"{{ _.baseUrl }}/crypto/cosmos","name":"Delete Historic Coin","description":"","method":"DELETE","body":{},"parameters":[],"headers":[],"authentication":{},"metaSortKey":-1658082382205,"isPrivate":false,"settingStoreCookies":true,"settingSendCookies":true,"settingDisableRenderRequestBody":false,"settingEncodeUrl":true,"settingRebuildPath":true,"settingFollowRedirects":"global","_type":"request"},{"_id":"env_22eb4645f68ee8dc901b7420e0d620a6087f3ef7","parentId":"wrk_8ea58a038c744f579cfef9ffbb7f3665","modified":1658671969322,"created":1658242406243,"name":"Base Environment","data":{},"dataPropertyOrder":{},"color":null,"isPrivate":false,"metaSortKey":1658242406243,"_type":"environment"},{"_id":"jar_22eb4645f68ee8dc901b7420e0d620a6087f3ef7","parentId":"wrk_8ea58a038c744f579cfef9ffbb7f3665","modified":1658665690206,"created":1658242406246,"name":"Default Jar","cookies":[{"key":"XSRF-TOKEN","value":"eyJpdiI6Im1UWXo3bUFPZGZKaEo0ZWJuSStIa1E9PSIsInZhbHVlIjoiaFpxa3JUSlZKK3RhWnFjcDlpVDZYWktvRGpmMFJxMUJGRnpGcEN6RGhjMllKWkRPdkFPNDAzbThnSEE4WFQ1Z3BxQ29EZTk4NEc4bHM2MWdJQjV1MnRKRE5vY1Q5L3F4RU83eUw1Z2h4YjQrN2E5VFdMSmxGYVZ1ZWlEMm5MYWQiLCJtYWMiOiI0ZGNjMjc3YjIyNTUwYmEzZDQ3ZjA5MGE1MjY1YmRkYzdlYjFiM2U5NWU0MjM3ZWE4ODBhNzZlMDkzZWJmNGYyIiwidGFnIjoiIn0%3D","expires":"2022-07-24T14:28:10.000Z","maxAge":7200,"domain":"127.0.0.1","path":"/","extensions":["samesite=lax"],"hostOnly":true,"creation":"2022-07-24T12:28:10.201Z","lastAccessed":"2022-07-24T12:28:10.201Z","id":"4788279299254221"},{"key":"laravel_session","value":"eyJpdiI6IlQyeHNZaVkzc1VLWmxDc3RzcTJMa2c9PSIsInZhbHVlIjoiNE1DeWNxNDJ6MllRRFFESnRqNnZZQ0VvRUFhRUtUQ290Zk1HVnoyZURxeENkV3krYWhKZWlqd3Zxd3ZwbTNMdlUrUnE4QW52bGhoY05SQldnSGxxeWVodU9CQVEweVdDZklsZW1Cc1hxWVBvWHRhTVJJQnQwL1RtQmRVWUhKV2siLCJtYWMiOiJmZjk3ZGM0NGI0MmM3ZTQxNTJmNDgzYjJjZjljMWU5NWMzMDMzNDQzYmE0ZDYxOWQ2ZTdiOTIyY2FmMmIzZDE0IiwidGFnIjoiIn0%3D","expires":"2022-07-24T14:28:10.000Z","maxAge":7200,"domain":"127.0.0.1","path":"/","httpOnly":true,"extensions":["samesite=lax"],"hostOnly":true,"creation":"2022-07-24T12:28:10.202Z","lastAccessed":"2022-07-24T12:28:10.202Z","id":"8678112103789957"}],"_type":"cookie_jar"},{"_id":"spc_11343316bf6e426bbce042b01e8e7aae","parentId":"wrk_8ea58a038c744f579cfef9ffbb7f3665","modified":1658242406237,"created":1658242406237,"fileName":"Dacxi Crypto","contents":"","contentType":"yaml","_type":"api_spec"},{"_id":"env_40a1be221a9640a19cf2686809c53b99","parentId":"env_22eb4645f68ee8dc901b7420e0d620a6087f3ef7","modified":1658681594920,"created":1658671940963,"name":"Developer","data":{"baseUrl":"http://127.0.0.1:8000/api"},"dataPropertyOrder":{"&":["baseUrl"]},"color":"#0011ff","isPrivate":false,"metaSortKey":1658671940963,"_type":"environment"},{"_id":"env_2233b5fed43c47c2958cac2ce7026595","parentId":"env_22eb4645f68ee8dc901b7420e0d620a6087f3ef7","modified":1658681599038,"created":1658672180228,"name":"Heroku","data":{"baseUrl":"https://crypto-historic-price.herokuapp.com/api"},"dataPropertyOrder":{"&":["baseUrl"]},"color":"#1eff00","isPrivate":false,"metaSortKey":1658672180228,"_type":"environment"}]}